COPYING
COPYING.LESSER
MANIFEST.in
README.ipynb
README.md
README.rst
VERSION
requirements.commands.txt
requirements.notebook.txt
requirements.pytest.txt
requirements.setup.txt
requirements.txt
setup.py
test-requirements.txt
tox.ini
zetuprc
test/conftest.py
test/test_modules.py
test/test_notebook.py
test/test_object.py
test/test_zetup_config.py
zetup/__init__.py
zetup/__main__.py
zetup/annotate.py
zetup/conda.py
zetup/config.py
zetup/dist.py
zetup/entry_point.py
zetup/error.py
zetup/extras.py
zetup/func.py
zetup/modules.py
zetup/object.py
zetup/package.py
zetup/program.py
zetup/requires.py
zetup/resolve.py
zetup/script.py
zetup/test_classpackage.py
zetup/version.py
zetup/zetup.py
zetup/zetup_config.py
zetup.egg-info/PKG-INFO
zetup.egg-info/SOURCES.txt
zetup.egg-info/dependency_links.txt
zetup.egg-info/entry_points.txt
zetup.egg-info/requires.txt
zetup.egg-info/top_level.txt
zetup/classes/__init__.py
zetup/classes/member_module.py
zetup/classes/package.py
zetup/classes/test/__init__.py
zetup/classes/test/Class/__init__.py
zetup/classes/test/Class/methods.py
zetup/commands/__init__.py
zetup/commands/command.py
zetup/commands/conda.py
zetup/commands/del_.py
zetup/commands/dev.py
zetup/commands/error.py
zetup/commands/pytest.py
zetup/commands/run.py
zetup/commands/test.py
zetup/commands/tox.py
zetup/commands/make/__init__.py
zetup/commands/make/templates/.travis.yml.jinja
zetup/commands/make/templates/VERSION.jinja
zetup/commands/make/templates/__init__.py.jinja
zetup/commands/make/templates/setup.py.jinja
zetup/commands/make/templates/tox.ini.jinja
zetup/commands/make/templates/package/zetup_config.py.jinja
zetup/doc/__init__.py
zetup/notebook/__init__.py
zetup/notebook/jinja.py
zetup/pip/__init__.py
zetup/pip/errors.py
zetup/pip/test_errors.py
zetup/process/__init__.py
zetup/process/scons.py
zetup/zfg/__init__.py
zetup/zfg/data.py
zetup/zfg/file.py
zetup/zfg/line.py
zetup/zfg/parser.py
zetup/zfg/test.zfg