Metadata-Version: 2.1
Name: zetup
Version: 0.2.64
Summary: Zimmermann's Extensible Tools for Unified Project_setups
Home-page: https://github.com/zimmermanncode/zetup
Author: Stefan Zimmermann
Author-email: user@zimmermann.co
License: LGPLv3
Keywords: zetup,project,tools,config,ini,setup,requirements,extras,packages,package,toplevel,object,meta,subprocess,process,popen,call,python3,python3
Platform: UNKNOWN
Classifier: Development Status :: 3 - Alpha
Classifier: Intended Audience :: Developers
Classifier: License :: OSI Approved :: GNU Library or Lesser General Public License (LGPL)
Classifier: Operating System :: OS Independent
Classifier: Topic :: Software Development
Classifier: Topic :: Utilities
Classifier: Programming Language :: Python
Classifier: Programming Language :: Python :: 2
Classifier: Programming Language :: Python :: 2.7
Classifier: Programming Language :: Python :: 3
Classifier: Programming Language :: Python :: 3.5
Classifier: Programming Language :: Python :: 3.6
Classifier: Programming Language :: Python :: 3.7
Provides-Extra: commands
Provides-Extra: notebook
Provides-Extra: pytest
Provides-Extra: all
